faros_config/__init__.py
faros_config/bastion.py
faros_config/cluster.py
faros_config/common.py
faros_config/config.py
faros_config/network.py
faros_config/proxy.py
faros_config/inventory/__init__.py
faros_config/inventory/cli.py
faros_config/inventory/config.py
faros_config/inventory/inventory.py
faros_config/inventory/ipam.py
faros_config/ui/__init__.py
faros_config/ui/api_bp.py
faros_config/ui/app.py
faros_config/ui/config.py
faros_config/ui/form.py
faros_config/ui/form_bp.py
faros_config/ui/static/css/.gitkeep
faros_config/ui/static/css/patternfly-additions.min.css
faros_config/ui/static/css/patternfly.min.css
faros_config/ui/static/fonts/.gitkeep
faros_config/ui/static/fonts/fontawesome-webfont.eot
faros_config/ui/static/fonts/fontawesome-webfont.svg
faros_config/ui/static/fonts/fontawesome-webfont.ttf
faros_config/ui/static/fonts/fontawesome-webfont.woff
faros_config/ui/static/fonts/fontawesome-webfont.woff2
faros_config/ui/static/js/.gitkeep
faros_config/ui/static/js/bootstrap.min.js
faros_config/ui/static/js/jquery.min.js
faros_config/ui/static/js/patternfly.min.js
faros_config/ui/templates/base.html
faros_config/ui/templates/failed.html
faros_config/ui/templates/form.html
faros_config/ui/templates/form_macros.html
faros_config/ui/templates/validate.html
faros_config-0.2.0.dist-info/LICENSE
faros_config-0.2.0.dist-info/METADATA
faros_config-0.2.0.dist-info/WHEEL
faros_config-0.2.0.dist-info/entry_points.txt
faros_config-0.2.0.dist-info/top_level.txt
faros_config-0.2.0.dist-info/RECORD
