Metadata-Version: 2.1
Name: faros-config
Version: 0.2.0
Summary: Project Faros configuration library and web application.
Home-page: https://faros.dev
Author: James Harmison
Author-email: jharmison@redhat.com
License: GNU GPL v3
Platform: UNKNOWN
Requires-Python: >=3.6
Requires-Dist: Flask (==1.1.2)
Requires-Dist: PyYAML (==5.3.1)
Requires-Dist: pydantic (==1.7.3)
Requires-Dist: Flask-WTF (==0.14.3)
